{
  "slug": "rd-net-propre",
  "i18n": {
    "default": "fr",
    "languages": [
      "fr",
      "en",
      "es",
      "ar"
    ]
  },
  "branding": {
    "logo": "https://xklic-media.s3.fr-par.scw.cloud/sites/rd-net-propre/logo-d0f2181d.png",
    "icon": "https://xklic-media.s3.fr-par.scw.cloud/sites/rd-net-propre/logo-d0f2181d.png",
    "logoAlt": "RD NET&PROPRE — شركة تنظيف في باريس",
    "logoTwoTone": {
      "first": "#1c6b57",
      "rest": "#c79a3f"
    },
    "tagline": "تنظيف احترافي · باريس ومنطقة إيل دو فرانس",
    "colors": {
      "brand": "#1c6b57",
      "accent": "#c79a3f",
      "neutral": "warm"
    },
    "logoScale": 1.35
  },
  "entreprise": {
    "nom": "RD NET&PROPRE",
    "statut": "EI",
    "siret": "99339068100019",
    "ape": "81.21Z",
    "apeLabel": "التنظيف الاعتيادي للمباني",
    "tva": {
      "regime": "franchise"
    }
  },
  "seo": {
    "schemaType": "CleaningService",
    "ville": "Paris"
  },
  "meta": {
    "title": "شركة تنظيف في باريس ومنطقة إيل دو فرانس",
    "description": "RD NET&PROPRE تنظّف العمارات والمكاتب والزجاج والمنازل في كامل إيل دو فرانس. تنظيف منزلي من 35 €/الساعة، عرض سعر مجاني خلال 24 ساعة، 6 أيام في الأسبوع.",
    "keywords": [
      "شركة تنظيف باريس",
      "تنظيف عمارات إيل دو فرانس",
      "تنظيف مكاتب باريس",
      "تنظيف زجاج باريس",
      "تنظيف منزلي باريس",
      "تنظيف الأجزاء المشتركة",
      "تنظيف بعد الأشغال باريس",
      "خدمات تنظيف إيل دو فرانس"
    ]
  },
  "pages": [
    {
      "slug": "",
      "label": "الرئيسية",
      "navHidden": true,
      "blocks": [
        {
          "type": "hero",
          "variant": "carte",
          "content": {
            "showSocial": true,
            "eyebrow": "شركة تنظيف · باريس وإيل دو فرانس",
            "titre": "أماكن ناصعة النظافة، في عهدة فريق",
            "titreAccent": "جادّ وكتوم",
            "accroche": "عمارات، مكاتب، محلات ومنازل: تعتني RD NET&PROPRE بأماكنكم بمنهجية، من مدخل العمارة إلى زجاج المكتب، في كامل إيل دو فرانس.",
            "trust": [
              {
                "icone": "Building2",
                "label": "عمارات وشركات"
              },
              {
                "icone": "Clock",
                "label": "6 أيام/أسبوع · 8ص – 10م"
              },
              {
                "icone": "ShieldCheck",
                "label": "فريق جدير بالثقة"
              },
              {
                "icone": "MapPin",
                "label": "كل إيل دو فرانس"
              }
            ],
            "card": {
              "label": "تنظيف منزلي",
              "prix": "35 €",
              "unite": "/ ساعة",
              "mention": "عرض سعر مجاني لباقي الخدمات",
              "points": [
                "تدخّلات من الاثنين إلى السبت، 8ص – 10م",
                "عرض سعر واضح خلال 24 ساعة",
                "عمّال قارّون وكتومون",
                "المعدات والمواد مُوفَّرة"
              ],
              "rating": {
                "label": "في خدمتكم في كامل المنطقة"
              }
            },
            "ctaPrimaire": {
              "label": "اطلب عرض سعر مجاني",
              "href": "/contact"
            },
            "ctaSecondaire": {
              "label": "اكتشف خدماتنا",
              "href": "/services"
            }
          }
        },
        {
          "type": "services",
          "content": {
            "eyebrow": "خدماتنا",
            "titre": "مزوّد واحد لكل نوع من الأماكن",
            "intro": "من التنظيف الدوري للأجزاء المشتركة إلى الترميم الشامل بعد ورشة، نغطّي حاجيات متصرّفي العمارات والشركات والأفراد في منطقة باريس.",
            "items": [
              {
                "nom": "العمارات والأجزاء المشتركة",
                "icone": "Building2",
                "priceHint": "حسب عرض السعر",
                "description": "مداخل، أدراج، بسطات، مصاعد وزجاج داخلي تُصان وفق جدول منتظم، مع مسؤول وحيد لمتصرّف العمارة.",
                "href": "/nettoyage-copropriete"
              },
              {
                "nom": "المكاتب والمحلات المهنية",
                "icone": "Briefcase",
                "priceHint": "من 120 €",
                "description": "مكاتب ومطاعم ومطابخ مهنية تُنظَّف قبل الافتتاح أو بعد الإغلاق، دون تعطيل نشاطكم.",
                "href": "/nettoyage-professionnels"
              },
              {
                "nom": "تنظيف الزجاج",
                "icone": "Sparkles",
                "priceHint": "من 100 €",
                "description": "واجهات وزجاج ونوافذ تصبح صافية من الجهتين، للمحلات كما للأفراد.",
                "href": "/nettoyage-vitres"
              },
              {
                "nom": "تنظيف منزلي",
                "icone": "Home",
                "priceHint": "من 35 €/الساعة",
                "description": "صيانة منتظمة أو ظرفية لمنزلكم، تُوكل دائماً إلى الشخص نفسه، منتبهٍ لعاداتكم.",
                "href": "/menage-domicile"
              },
              {
                "nom": "الأرائك والكراسي والسجاد",
                "icone": "Sofa",
                "priceHint": "من 70 €",
                "description": "أقمشة تستعيد نضارتها بالحقن والاستخراج: مقاعد مُطهَّرة، بقع مُعالَجة، سجاد يُغسل ليفاً ليفاً.",
                "href": "/nettoyage-textiles"
              },
              {
                "nom": "الترميم بعد الأشغال",
                "icone": "Hammer",
                "priceHint": "من 300 €",
                "description": "بعد ورشة أو انتقال، يُستعاد المكان غرفةً غرفة حتى تسليم المفاتيح.",
                "href": "/remise-en-etat"
              },
              {
                "nom": "التطهير والتنظيف الحيوي",
                "icone": "ShieldPlus",
                "priceHint": "حسب عرض السعر",
                "description": "تنظيف وتطهير احترافي: تطبيق بروتوكولات النظافة الاستشفائية والتنظيف الحيوي، بأساليب ومواد ملائمة.",
                "href": "/nettoyage-professionnels"
              }
            ],
            "cta": {
              "label": "شاهد كل الخدمات",
              "href": "/services"
            }
          },
          "variant": "mosaique"
        },
        {
          "type": "galerie",
          "variant": "grille",
          "content": {
            "eyebrow": "بالصور",
            "titre": "تنظيف RD NET&PROPRE في الميدان",
            "intro": "لمحة عن تدخّلاتنا، من الأجزاء المشتركة للعمارة إلى زجاج المكاتب والأرائك التي تستعيد نضارتها.",
            "ratio": "4/3",
            "images": [
              {
                "image": {
                  "url": "https://xklic-media.s3.fr-par.scw.cloud/sites/rd-net-propre/service-menage.png",
                  "alt": "فريق RD NET&PROPRE يكنس ويغسل أرضية صالون مضيء"
                },
                "titre": "تنظيف المنزل وصيانته"
              },
              {
                "image": {
                  "url": "https://xklic-media.s3.fr-par.scw.cloud/sites/rd-net-propre/service-bureaux.png",
                  "alt": "فضاء مكاتب نظيف ومرتّب بعد مرور RD NET&PROPRE"
                },
                "titre": "المكاتب والفضاءات المهنية"
              },
              {
                "image": {
                  "url": "https://xklic-media.s3.fr-par.scw.cloud/sites/rd-net-propre/service-canape.png",
                  "alt": "تنظيف وسادة أريكة بالشفط العميق"
                },
                "titre": "الأرائك والكراسي والسجاد"
              },
              {
                "image": {
                  "url": "https://xklic-media.s3.fr-par.scw.cloud/sites/rd-net-propre/service-vitres-facade.png",
                  "alt": "تقنيّون ينظّفون زجاج واجهة عمارة على ارتفاع"
                },
                "titre": "الزجاج وواجهات العمارات"
              }
            ]
          }
        },
        {
          "type": "contenu",
          "content": {
            "eyebrow": "من نحن",
            "titre": "شركة فتيّة من منطقة باريس،",
            "titreAccent": "دقيقة في التفاصيل",
            "paragraphes": [
              "وُلدت RD NET&PROPRE من الرغبة في أن نقدّم لمتصرّفي العمارات والشركات والعائلات في إيل دو فرانس تنظيفاً يصمد فعلاً في الزمن، بعيداً عن الأعمال المتسرّعة. انطلاقاً من باريس، نغطّي كامل المنطقة للصيانة الاعتيادية كما لعمليات الترميم الظرفية.",
              "منهجنا بسيط: عمّال قارّون بدل مناوبة مجهولة، ومُحاور يعرف أماكنكم، ومراقبة منهجية قبل المغادرة. هذا ما يُبقي المدخل نظيفاً أسبوعاً بعد أسبوع، ويجعل المكتب يستقبل فرقكم في أفضل الظروف.",
              "نستقبل زبائننا بالفرنسية والإنجليزية والإسبانية والعربية: يمكن لكلٍّ أن يصف حاجته بلغته وأن يتلقّى عرض سعر واضحاً بلا تعقيد."
            ],
            "image": {
              "url": "https://xklic-media.s3.fr-par.scw.cloud/sites/rd-net-propre/qui-sommes-nous.png",
              "alt": "صورة RD NET&PROPRE — معدات تنظيف احترافية في مكتب مضيء"
            },
            "imagePosition": "left",
            "imageRatio": "16/10",
            "imageCard": true,
            "ctaPrimaire": {
              "label": "تعرّف علينا",
              "href": "/a-propos"
            }
          }
        },
        {
          "type": "etapes",
          "content": {
            "eyebrow": "كيف نعمل",
            "titre": "من اتصالكم إلى مكان ناصع",
            "items": [
              {
                "icone": "Phone",
                "titre": "تصفون المكان",
                "texte": "عبر الهاتف أو واتساب أو النموذج، تحدّدون نوع الفضاء والمساحة والوتيرة المطلوبة."
              },
              {
                "icone": "FileText",
                "titre": "عرض سعر واضح خلال 24 ساعة",
                "texte": "نعيد إليكم اقتراحاً مفصّلاً، بسعرٍ ثابت وبرنامج تدخّل مناسب."
              },
              {
                "icone": "Sparkles",
                "titre": "التدخّل ثم المراقبة",
                "texte": "يتدخّل الفريق بمعدّاته ويتحقّق من كل منطقة قبل المغادرة. تظهر النتيجة منذ الزيارة الأولى."
              }
            ]
          },
          "variant": "timeline-verticale"
        },
        {
          "type": "zone",
          "mode": "carte",
          "content": {
            "titre": "باريس منطلقاً، وإيل دو فرانس ميداناً",
            "intro": "نعمل داخل باريس وفي أقاليم المنطقة الثمانية، من الحزام الأول إلى الحزام الثاني. تنقّلٌ إلى أطراف المنطقة لا يخيفنا: أخبرونا فقط أين يقع المكان.",
            "rayonKm": 60,
            "mapEmbedUrl": "https://www.openstreetmap.org/export/embed.html?bbox=1.44%2C48.12%2C3.56%2C49.24&layer=mapnik&marker=48.8566%2C2.3522",
            "zones": [
              {
                "region": "باريس المدينة",
                "principale": "Paris",
                "villes": [
                  "باريس، من الدائرة 1 إلى 20"
                ]
              },
              {
                "region": "الحزام الأول",
                "principale": "Boulogne-Billancourt",
                "villes": [
                  "Boulogne-Billancourt",
                  "Neuilly-sur-Seine",
                  "Levallois-Perret",
                  "Nanterre",
                  "Courbevoie",
                  "Montreuil",
                  "Saint-Denis",
                  "Aubervilliers",
                  "Créteil",
                  "Vitry-sur-Seine",
                  "Ivry-sur-Seine"
                ]
              },
              {
                "region": "الحزام الثاني",
                "principale": "Versailles",
                "villes": [
                  "Versailles",
                  "Argenteuil",
                  "Cergy",
                  "Évry-Courcouronnes",
                  "Meaux",
                  "Melun",
                  "Sarcelles",
                  "Saint-Germain-en-Laye"
                ]
              }
            ]
          }
        },
        {
          "type": "faq",
          "content": {
            "titre": "أكثر ما يُسأل عنه",
            "items": [
              {
                "question": "هل تعملون أكثر مع المهنيين أم مع الأفراد؟",
                "reponse": "مع الاثنين. نصون الأجزاء المشتركة للعمارات ومحلات الشركات، ونعتني كذلك بمنازل الأفراد. لكل خدمة صفحتها الخاصة بتفاصيل ما تشمله."
              },
              {
                "question": "خلال أي مدة يمكن أن نبدأ؟",
                "reponse": "لتدخّل ظرفي، نقترح غالباً موعداً خلال الأسبوع. لعقد دوري، نضبط معاً جدولاً ثابتاً. أمّا عرض السعر فيصلكم خلال 24 ساعة."
              },
              {
                "question": "هل يجب توفير المعدات والمواد؟",
                "reponse": "لا، نأتي مجهّزين. وإن فضّلتم استعمال مواد معيّنة، مثلاً لسطح حسّاس أو بوجود أطفال، يكفي أن تشيروا إلى ذلك عند إعداد عرض السعر."
              },
              {
                "question": "بأي لغات يمكن التواصل معكم؟",
                "reponse": "بالفرنسية والإنجليزية والإسبانية والعربية. صِفوا حاجتكم باللغة التي تناسبكم، وسيأتي الجواب بها نفسها."
              }
            ]
          },
          "variant": "deux-colonnes"
        },
        {
          "type": "cta",
          "content": {
            "titre": "مكان تريدون إعادته ناصعاً؟",
            "sousTitre": "هاتف أو واتساب أو النموذج الإلكتروني: يصلكم تقديركم المجاني خلال 24 ساعة.",
            "ctaPrimaire": {
              "label": "اطلب عرض سعر مجاني",
              "href": "/contact"
            },
            "ctaSecondaire": {
              "label": "+33 7 48 32 20 29",
              "href": "tel:+33748322029"
            },
            "lien": {
              "label": "أو راسلونا عبر واتساب ←",
              "href": "https://wa.me/33748322029"
            }
          },
          "variant": "encadre"
        }
      ]
    },
    {
      "slug": "services",
      "label": "الخدمات",
      "meta": {
        "title": "خدمات تنظيف في باريس وإيل دو فرانس",
        "description": "عمارات، مكاتب، زجاج، تنظيف منزلي، أقمشة وترميم بعد الأشغال: تفاصيل كل خدمة تنظيف من RD NET&PROPRE في إيل دو فرانس."
      },
      "blocks": [
        {
          "type": "pageHero",
          "content": {
            "eyebrow": "خدماتنا",
            "titre": "لكل مكان تنظيفه الخاص",
            "intro": "نلائم المنهج والوتيرة والمواد مع طبيعة الفضاء: مدخل عمارة لا يُصان مثل مكتب، ولا أريكة مثل واجهة محل. إليكم مجالات عملنا الستة.",
            "ctaPrimaire": {
              "label": "اطلب عرض سعر",
              "href": "/contact"
            },
            "ctaSecondaire": {
              "label": "شاهد الأسعار",
              "href": "/tarifs"
            }
          }
        },
        {
          "type": "services",
          "content": {
            "eyebrow": "الشركات ومتصرّفو العمارات",
            "titre": "للعمارات والشركات",
            "intro": "تدخّلات مبرمَجة، مُحاور وحيد وتقارير واضحة لمن يديرون المباني والمحلات.",
            "items": [
              {
                "nom": "العمارات والأجزاء المشتركة",
                "icone": "Building2",
                "priceHint": "حسب عرض السعر",
                "description": "مداخل، بيوت درج، بسطات، مصاعد وزجاج داخلي: صيانة منتظمة تُثمّن العمارة وتطمئن السكان.",
                "href": "/nettoyage-copropriete"
              },
              {
                "nom": "المكاتب والمحلات المهنية",
                "icone": "Briefcase",
                "priceHint": "من 120 €",
                "description": "مكاتب ومطاعم ومطابخ مهنية، تُنظَّف خارج ساعات عملكم، مع احترام قواعد النظافة.",
                "href": "/nettoyage-professionnels"
              },
              {
                "nom": "تنظيف الزجاج",
                "icone": "Sparkles",
                "priceHint": "من 100 €",
                "description": "واجهات المحلات والواجهات الزجاجية ونوافذ المكاتب تُنظَّف بلا آثار، مع معالجة الارتفاعات بأمان.",
                "href": "/nettoyage-vitres"
              },
              {
                "nom": "التطهير والتنظيف الحيوي",
                "icone": "ShieldPlus",
                "priceHint": "حسب عرض السعر",
                "description": "تنظيف وتطهير احترافي: تطبيق بروتوكولات النظافة الاستشفائية والتنظيف الحيوي، بأساليب ومواد ملائمة.",
                "href": "/nettoyage-professionnels"
              }
            ]
          },
          "variant": "grille-icones"
        },
        {
          "type": "services",
          "content": {
            "eyebrow": "الأفراد",
            "titre": "لمنزلكم وأقمشتكم",
            "intro": "العناية نفسها بالتفاصيل، محمولةً إلى البيت: صيانة مستمرّة وأثاث يستعيد نضارته.",
            "items": [
              {
                "nom": "تنظيف منزلي",
                "icone": "Home",
                "priceHint": "من 35 €/الساعة",
                "description": "صيانة أسبوعية أو ظرفية: أرضيات ومطبخ وحمّام وغبار وفق تعليماتكم، على يد عاملة قارّة.",
                "href": "/menage-domicile"
              },
              {
                "nom": "الأرائك والكراسي والسجاد",
                "icone": "Sofa",
                "priceHint": "من 70 €",
                "description": "حقن واستخراج في العمق: تخرج الأقمشة مُطهَّرة، خاليةً من الروائح، وتجفّ خلال ساعات. سجاد يُغسل حسب اللِيف.",
                "href": "/nettoyage-textiles"
              },
              {
                "nom": "الترميم بعد الأشغال",
                "icone": "Hammer",
                "priceHint": "من 300 €",
                "description": "بعد ورشة أو قبل جرد الخروج: غبار الورشة وآثار الطلاء والأرضيات تُستعاد حتى آخر ركن.",
                "href": "/remise-en-etat"
              }
            ],
            "cta": {
              "label": "قدّر ميزانيتي",
              "href": "/tarifs"
            }
          },
          "variant": "grille-icones"
        },
        {
          "type": "cta",
          "content": {
            "titre": "لا تعرفون في أي خانة تضعون حاجتكم؟",
            "sousTitre": "صِفوا لنا المكان والهدف: نوجّهكم إلى الخدمة المناسبة ونضع لها سعراً.",
            "ctaPrimaire": {
              "label": "صِف حاجتي",
              "href": "/contact"
            },
            "ctaSecondaire": {
              "label": "+33 7 48 32 20 29",
              "href": "tel:+33748322029"
            }
          },
          "variant": "encadre"
        }
      ]
    },
    {
      "slug": "nettoyage-copropriete",
      "label": "العمارات",
      "navHidden": true,
      "meta": {
        "title": "تنظيف العمارات والأجزاء المشتركة باريس",
        "description": "صيانة الأجزاء المشتركة في إيل دو فرانس: مداخل، أدراج، بسطات، مصاعد وزجاج داخلي. جدول منتظم، مسؤول وحيد، عرض سعر مجاني."
      },
      "service": {
        "name": "تنظيف العمارات والأجزاء المشتركة",
        "description": "صيانة منتظمة للأجزاء المشتركة للمباني السكنية في إيل دو فرانس.",
        "serviceType": "تنظيف الأجزاء المشتركة",
        "priceFrom": "حسب عرض السعر"
      },
      "blocks": [
        {
          "type": "pageHero",
          "content": {
            "eyebrow": "العمارات والمباني السكنية",
            "titre": "أجزاء مشتركة نظيفة دائماً",
            "intro": "العمارة المعتنى بها تظهر من المدخل. نصون أجزاءكم المشتركة بإيقاع منتظم، من أجل سكّان راضين وممتلكات محفوظة.",
            "breadcrumb": [
              {
                "label": "الرئيسية",
                "href": "/"
              },
              {
                "label": "الخدمات",
                "href": "/services"
              },
              {
                "label": "العمارات"
              }
            ],
            "ctaPrimaire": {
              "label": "اطلب عرض سعر",
              "href": "/contact"
            },
            "ctaSecondaire": {
              "label": "+33 7 48 32 20 29",
              "href": "tel:+33748322029"
            }
          }
        },
        {
          "type": "contenu",
          "content": {
            "titre": "صيانة مُصمَّمة لمتصرّفي العمارات والسكان",
            "paragraphes": [
              "صيانة الأجزاء المشتركة هي صلب عملنا مع عمارات منطقة باريس. نتكفّل بكنس وغسل المداخل وبيوت الدرج والبسطات، وإزالة الغبار عن الدرابزين وصناديق البريد والمفاتيح الكهربائية، وتنظيف مقصورات المصاعد والزجاج الداخلي؛ وتدبير الحاويات في أيام الجمع يمكن أن يُضاف حسب العقد.",
              "تتلقّى كل عمارة جدولاً ثابتاً، ومن الأفضل الفريقَ نفسه من أسبوع إلى آخر: يعرفون الزوايا وعادات العمارة، ويبلّغون المتصرّف بما يستحقّ الانتباه. تحتفظون بمُحاور وحيد يمكن بلوغه، وبتقرير واضح لما أُنجز.",
              "تتلاءم الوتيرة مع حياة العمارة: مرور أسبوعي، أو كل أسبوعين، أو عدة مرات أسبوعياً للعمارات كثيرة الحركة. نُعدّ عرض السعر بعد معاينة المكان، لسعرٍ عادل وبلا مفاجآت."
            ]
          }
        },
        {
          "type": "faq",
          "content": {
            "titre": "أسئلة متصرّفي العمارات",
            "items": [
              {
                "question": "هل تقترحون عقود صيانة منتظمة؟",
                "reponse": "نعم، وهي الصيغة الأكثر شيوعاً في العمارات: جدول ثابت، ووتيرة متّفق عليها مع المتصرّف أو مجلس العمارة، وفوترة شهرية واضحة. وتبقى التدخّلات الظرفية ممكنة لحاجة معزولة."
              },
              {
                "question": "هل تتكفّلون بإخراج النفايات وتنظيف مستودع الحاويات؟",
                "reponse": "خيار متكرّر في عقودنا. إخراج الحاويات وإعادتها في أيام الجمع، وغسل المستودع، وتعقيم ظرفي، يمكن أن تُدرَج جميعها: نبيّن ذلك بوضوح في عرض السعر."
              },
              {
                "question": "كيف يتابع المتصرّف جودة العمل؟",
                "reponse": "لديكم مُحاور وحيد معنا وتقرير عن التدخّلات. أي ملاحظة من ساكن تصلنا مباشرة ونصحّح منذ المرور التالي."
              }
            ]
          },
          "variant": "deux-colonnes"
        },
        {
          "type": "services",
          "content": {
            "titre": "حاجيات أخرى لعمارتكم",
            "items": [
              {
                "nom": "تنظيف الزجاج",
                "icone": "Sparkles",
                "description": "مداخل زجاجية وأبواب ونوافذ الأجزاء المشتركة.",
                "href": "/nettoyage-vitres"
              },
              {
                "nom": "الترميم بعد الأشغال",
                "icone": "Hammer",
                "description": "أجزاء مشتركة تُستعاد بعد أشغال أو ضرر.",
                "href": "/remise-en-etat"
              },
              {
                "nom": "المكاتب والمحلات المهنية",
                "icone": "Briefcase",
                "description": "غرفة الحارس أو قاعة مشتركة أو مكتب التسيير.",
                "href": "/nettoyage-professionnels"
              }
            ]
          },
          "variant": "grille-icones"
        },
        {
          "type": "cta",
          "content": {
            "titre": "اعهدوا بأجزائكم المشتركة إلى فريق منتظم",
            "sousTitre": "أرسلوا لنا العنوان وعدد الطوابق: نأتي للمعاينة ونضع سعر العقد.",
            "ctaPrimaire": {
              "label": "اطلب عرض سعر",
              "href": "/contact"
            },
            "ctaSecondaire": {
              "label": "+33 7 48 32 20 29",
              "href": "tel:+33748322029"
            }
          },
          "variant": "encadre"
        }
      ]
    },
    {
      "slug": "nettoyage-professionnels",
      "label": "مكاتب وشركات",
      "navHidden": true,
      "meta": {
        "title": "تنظيف مكاتب ومحلات مهنية في باريس",
        "description": "تنظيف المكاتب والمطاعم والمطابخ المهنية في إيل دو فرانس، من 120 €. تدخّلات خارج ساعات العمل، نظافة مُتقنة، عرض سعر خلال 24 ساعة."
      },
      "service": {
        "name": "تنظيف المكاتب والمحلات المهنية",
        "description": "صيانة المكاتب والمطاعم والمطابخ المهنية في إيل دو فرانس.",
        "serviceType": "تنظيف المحلات المهنية",
        "priceFrom": 120
      },
      "blocks": [
        {
          "type": "pageHero",
          "content": {
            "eyebrow": "شركات ومحلات ومطاعم",
            "titre": "محلات نظيفة، دون تعطيل نشاطكم",
            "intro": "بيئة عمل صحّية تُعطي الانطباع الأول لفِرقكم وزبائنكم. نصون مكاتبكم وفضاءاتكم المهنية قبل الافتتاح أو بعد الإغلاق.",
            "breadcrumb": [
              {
                "label": "الرئيسية",
                "href": "/"
              },
              {
                "label": "الخدمات",
                "href": "/services"
              },
              {
                "label": "مكاتب وشركات"
              }
            ],
            "ctaPrimaire": {
              "label": "اطلب عرض سعر",
              "href": "/contact"
            },
            "ctaSecondaire": {
              "label": "+33 7 48 32 20 29",
              "href": "tel:+33748322029"
            }
          }
        },
        {
          "type": "contenu",
          "content": {
            "titre": "مكاتب ومطاعم ومطابخ مهنية",
            "paragraphes": [
              "نتدخّل في فضاءات العمل بكل أحجامها: طوابق مكاتب، عيادات، قاعات اجتماعات، مرافق صحّية وفضاءات استقبال. يشمل البروتوكول إفراغ السلال، وإزالة الغبار عن المكاتب، وغسل الأرضيات، وتعقيم نقاط التماس، وصيانة المرافق الصحّية، مع تجديد المستهلكات إن رغبتم.",
              "في المطاعم يرتفع مستوى الصرامة: إزالة الدهون عن الأسطح، وتنظيف القاعات والمطابخ المهنية مع احترام قواعد النظافة، وأرضيات مانعة للانزلاق تُعالَج بالمواد المناسبة. نلائم مرورنا مع خدمتكم، باكراً صباحاً أو متأخراً مساءً، كي لا نعيق استقبال الجمهور أبداً.",
              "تنطلق الخدمة من 120 € وتتكيّف مع المساحة والوتيرة ومستوى المتطلّبات. عقدٌ دوري يضمن الفريق نفسه ونتيجة ثابتة، أسبوعاً بعد أسبوع.",
              "نتكفّل أيضاً بالتنظيف والتطهير الاحترافي للبيئات الحسّاسة: تطبيق بروتوكولات النظافة الاستشفائية والتنظيف الحيوي، بأساليب ومواد ملائمة لكل سطح. حلٌّ للعيادات والمختبرات وقاعات العلاج وكل محلّ تتطلّب فيه النظافة أعلى مستوى."
            ]
          }
        },
        {
          "type": "faq",
          "content": {
            "titre": "أسئلة الشركات وأصحاب المطاعم",
            "items": [
              {
                "question": "هل يمكنكم التدخّل خارج ساعات العمل؟",
                "reponse": "نعم، بل هي القاعدة لدى أغلب زبائننا المهنيين. باكراً صباحاً أو مساءً أو ليلاً حسب نشاطكم: نضبط المرور حول أوقاتكم الأقل ازدحاماً كي لا نزعج الزبائن ولا الموظّفين."
              },
              {
                "question": "هل تحترمون متطلّبات النظافة في المطبخ المهني؟",
                "reponse": "نستعمل مواد وطرقاً ملائمة للأسطح الغذائية ولإزالة الدهون، ونتدخّل ضمن منطق قواعد نظافة المطاعم. وتفاصيل المناطق المُعالَجة تظهر في عرض السعر."
              },
              {
                "question": "هل تُفوتَر تنظيف المكاتب بالساعة أم جزافاً؟",
                "reponse": "غالباً جزافاً، محسوباً على المساحة والوتيرة، لميزانية قابلة للتوقّع. ولحاجة ظرفية أو مساحة كبيرة، يمكن أيضاً التسعير بالتدخّل."
              }
            ]
          },
          "variant": "deux-colonnes"
        },
        {
          "type": "services",
          "content": {
            "titre": "للدمج مع محلّاتكم",
            "items": [
              {
                "nom": "تنظيف الزجاج",
                "icone": "Sparkles",
                "description": "واجهات ونوافذ المكاتب بلا آثار، ناحية الشارع كما الفناء.",
                "href": "/nettoyage-vitres"
              },
              {
                "nom": "الترميم بعد الأشغال",
                "icone": "Hammer",
                "description": "محلّ يُستعاد بعمق بعد تهيئة أو قبل تسليم.",
                "href": "/remise-en-etat"
              },
              {
                "nom": "الأرائك والكراسي",
                "icone": "Sofa",
                "description": "مقاعد الاستقبال وكراسي الاجتماعات مُطهَّرة.",
                "href": "/nettoyage-textiles"
              }
            ]
          },
          "variant": "grille-icones"
        },
        {
          "type": "cta",
          "content": {
            "titre": "عرض سعر لمكاتبكم أو محلّكم؟",
            "sousTitre": "بيّنوا المساحة وأوقاتكم: نقترح جدولاً وسعراً ثابتاً.",
            "ctaPrimaire": {
              "label": "اطلب عرض سعر",
              "href": "/contact"
            },
            "ctaSecondaire": {
              "label": "+33 7 48 32 20 29",
              "href": "tel:+33748322029"
            }
          },
          "variant": "encadre"
        }
      ]
    },
    {
      "slug": "nettoyage-vitres",
      "label": "الزجاج",
      "navHidden": true,
      "meta": {
        "title": "تنظيف الزجاج في باريس، من 100 €",
        "description": "تنظيف الزجاج للمهنيين والأفراد في إيل دو فرانس، من 100 €. واجهات وزجاج ونوافذ بلا آثار، من الجهتين. عرض سعر مجاني خلال 24 ساعة."
      },
      "service": {
        "name": "تنظيف الزجاج",
        "description": "تنظيف الزجاج والواجهات والنوافذ الزجاجية للمهنيين والأفراد في إيل دو فرانس.",
        "serviceType": "تنظيف الزجاج",
        "priceFrom": 100
      },
      "blocks": [
        {
          "type": "pageHero",
          "content": {
            "eyebrow": "مهنيون وأفراد",
            "titre": "يدخل الضوء، وتختفي الآثار",
            "intro": "زجاج نظيف يغيّر كل شيء: واجهة تدعو للدخول، مكتب أكثر إضاءة، صالون متجدّد. نغسل أسطحكم الزجاجية من الوجهين.",
            "breadcrumb": [
              {
                "label": "الرئيسية",
                "href": "/"
              },
              {
                "label": "الخدمات",
                "href": "/services"
              },
              {
                "label": "الزجاج"
              }
            ],
            "ctaPrimaire": {
              "label": "اطلب عرض سعر",
              "href": "/contact"
            },
            "ctaSecondaire": {
              "label": "+33 7 48 32 20 29",
              "href": "tel:+33748322029"
            }
          }
        },
        {
          "type": "contenu",
          "content": {
            "titre": "واجهات ونوافذ زجاجية وشبابيك",
            "paragraphes": [
              "ننظّف زجاج المحلات والشركات كما ننظّف زجاج المنازل: واجهات وعروض، أسقف زجاجية، نوافذ منزلقة، شبابيك ذات مربّعات، إطارات وحوافّ. يُغسل كل سطح من وجهيه، ثم يُراجَع في عكس الضوء كي لا نترك غشاوة ولا خطوطاً.",
              "بالنسبة لواجهات المحلات، يحافظ المرور المنتظم على صورة أنيقة تهمّ في اللحظة التي يتردّد فيها الزبون في دفع الباب. أمّا للأفراد فتكفي غالباً حملة تنظيف موسمية لاستعادة الوضوح في كامل المنزل. تُعالَج الأسطح المرتفعة بالمعدّات المناسبة وبأمان.",
              "تنطلق الخدمة من 100 € وتتوقّف على عدد الفتحات وسهولة الوصول إليها والوتيرة. نضع سعراً دقيقاً بعد معاينة الأسطح المطلوب معالجتها."
            ]
          }
        },
        {
          "type": "faq",
          "content": {
            "titre": "أسئلة حول تنظيف الزجاج",
            "items": [
              {
                "question": "هل تنظّفون واجهات المحلات بانتظام؟",
                "reponse": "نعم. يختار كثير من التجّار مروراً أسبوعياً أو كل أسبوعين للحفاظ على واجهة ناصعة دائماً. نتدخّل قبل الافتتاح كي لا نعيق الزبائن."
              },
              {
                "question": "هل تصلون إلى الزجاج المرتفع؟",
                "reponse": "نعالج الأسطح على ارتفاع معقول بالعصي والمعدّات المناسبة. أمّا التركيبات المعقّدة أو الواجهات الكبيرة فنقيّم سبل الوصول عند إعداد عرض السعر ونقترح الحلّ الأكثر أماناً."
              },
              {
                "question": "هل الإطارات والحوافّ مشمولة؟",
                "reponse": "نعم، يشمل التنظيف القوائم والحوافّ وآثار الإطارات: هذا ما يميّز غسلاً حقيقياً للزجاج عن مجرّد مسحة إسفنجة على الزجاج."
              }
            ]
          },
          "variant": "deux-colonnes"
        },
        {
          "type": "services",
          "content": {
            "titre": "كثيراً ما يُطلب مع",
            "items": [
              {
                "nom": "المكاتب والمحلات المهنية",
                "icone": "Briefcase",
                "description": "الصيانة الكاملة للمحلّ، بما فيه الزجاج.",
                "href": "/nettoyage-professionnels"
              },
              {
                "nom": "تنظيف منزلي",
                "icone": "Home",
                "description": "الزجاج مُدمَجاً في الصيانة المنتظمة للمنزل.",
                "href": "/menage-domicile"
              },
              {
                "nom": "العمارات والأجزاء المشتركة",
                "icone": "Building2",
                "description": "مداخل وأبواب زجاجية للمباني السكنية.",
                "href": "/nettoyage-copropriete"
              }
            ]
          },
          "variant": "grille-icones"
        },
        {
          "type": "cta",
          "content": {
            "titre": "ترغبون في رؤية أوضح؟",
            "sousTitre": "أحصوا نوافذكم وواجهاتكم وأرسلوا لنا العدد: يتبع عرض السعر خلال 24 ساعة.",
            "ctaPrimaire": {
              "label": "اطلب عرض سعر",
              "href": "/contact"
            },
            "ctaSecondaire": {
              "label": "+33 7 48 32 20 29",
              "href": "tel:+33748322029"
            }
          },
          "variant": "encadre"
        }
      ]
    },
    {
      "slug": "menage-domicile",
      "label": "تنظيف منزلي",
      "navHidden": true,
      "meta": {
        "title": "تنظيف منزلي في باريس، من 35 €/الساعة",
        "description": "تنظيف منزلي في إيل دو فرانس من 35 €/الساعة: صيانة منتظمة أو ظرفية، عاملة قارّة، تعليمات محترمة، معدات مُوفَّرة. عرض سعر مجاني خلال 24 ساعة."
      },
      "service": {
        "name": "تنظيف منزلي",
        "description": "صيانة منتظمة أو ظرفية للمنزل في إيل دو فرانس، من 35 €/الساعة.",
        "serviceType": "تنظيف منزلي",
        "priceFrom": 35
      },
      "blocks": [
        {
          "type": "pageHero",
          "content": {
            "eyebrow": "الأفراد",
            "titre": "منزل معتنى به، وبال مطمئنّ",
            "intro": "أن تعودوا إلى منزل أنيق دون أن تُنفقوا عطلتكم عليه: هذا ما نقدّمه لكم، مع عاملة قارّة تعرف عاداتكم.",
            "breadcrumb": [
              {
                "label": "الرئيسية",
                "href": "/"
              },
              {
                "label": "الخدمات",
                "href": "/services"
              },
              {
                "label": "تنظيف منزلي"
              }
            ],
            "ctaPrimaire": {
              "label": "اطلب عرض سعر",
              "href": "/contact"
            },
            "ctaSecondaire": {
              "label": "+33 7 48 32 20 29",
              "href": "tel:+33748322029"
            }
          }
        },
        {
          "type": "contenu",
          "content": {
            "titre": "صيانة منزلكم، على إيقاعكم",
            "paragraphes": [
              "سواء أردتم مروراً أسبوعياً أو تنظيفاً ظرفياً أو حملة تنظيف موسمية كبرى، نلائم الخدمة مع بيتكم. أرضيات ومطبخ وحمّام وغبار وزجاج داخلي وترتيب خفيف: تحدّدون الأولويات في الموعد الأول، ونحن ندوّنها ونتابعها في كل زيارة.",
              "نفضّل الشخص نفسه من مرة إلى أخرى. هذا ما يبني الثقة عند تسليم المفاتيح: تنتهي عاملتكم إلى معرفة البيت وأسطحه الحسّاسة وتفضيلاتكم في المواد. وبوجود أطفال أو حيوانات أليفة، نلائم بطبيعة الحال المواد المستعملة.",
              "ينطلق التنظيف المنزلي من 35 €/الساعة، مع توفير المعدات والمواد. تبقون أحراراً في تحديد الوتيرة ويمكنكم تغيير الإيقاع حسب الفصول. عرض السعر مجاني وبلا التزام."
            ]
          }
        },
        {
          "type": "faq",
          "content": {
            "titre": "أسئلة حول التنظيف المنزلي",
            "items": [
              {
                "question": "هل سيكون لديّ الشخص نفسه دائماً؟",
                "reponse": "هذه أولويتنا: نخصّص عاملة قارّة لمنزلكم كي تعرف مكانكم وتعليماتكم. وإن غابت، يتلقّى من يحلّ محلّها كل ملاحظاتكم مسبقاً."
              },
              {
                "question": "هل يمكن حجز تنظيف ظرفي بدل عقد منتظم؟",
                "reponse": "بالطبع. تنظيف ربيعي كبير، أو تهيئة قبل استقبال، أو بعد فترة مزدحمة: نتدخّل بشكل ظرفي، دون إلزام بالتكرار."
              },
              {
                "question": "هل تقدّمون الخصم الضريبي على التنظيف المنزلي؟",
                "reponse": "التنظيف في بيت فرد يندرج ضمن خدمات الأشخاص، لكن الميزة الضريبية تستلزم تصريحاً خاصاً. نخبركم بكل شفافية، عند إعداد عرض السعر، إن كانت خدمتكم تفتح هذا الحقّ أم لا."
              }
            ]
          },
          "variant": "deux-colonnes"
        },
        {
          "type": "services",
          "content": {
            "titre": "للمزيد في بيتكم",
            "items": [
              {
                "nom": "الأرائك والكراسي والسجاد",
                "icone": "Sofa",
                "description": "إعادة الحياة إلى الأقمشة التي لا تكفي الصيانة اليومية لإنعاشها.",
                "href": "/nettoyage-textiles"
              },
              {
                "nom": "تنظيف الزجاج",
                "icone": "Sparkles",
                "description": "تنظيف كبير للنوافذ لاستعادة الضوء.",
                "href": "/nettoyage-vitres"
              },
              {
                "nom": "الترميم بعد الأشغال",
                "icone": "Hammer",
                "description": "منزل يُستعاد بعمق بعد أشغال أو قبل انتقال.",
                "href": "/remise-en-etat"
              }
            ]
          },
          "variant": "grille-icones"
        },
        {
          "type": "cta",
          "content": {
            "titre": "ترغبون في راحة من التنظيف؟",
            "sousTitre": "أخبرونا بحجم المنزل والوتيرة المطلوبة: نقدّر الميزانية خلال 24 ساعة.",
            "ctaPrimaire": {
              "label": "اطلب عرض سعر",
              "href": "/contact"
            },
            "ctaSecondaire": {
              "label": "+33 7 48 32 20 29",
              "href": "tel:+33748322029"
            }
          },
          "variant": "encadre"
        }
      ]
    },
    {
      "slug": "nettoyage-textiles",
      "label": "أرائك وسجاد",
      "navHidden": true,
      "meta": {
        "title": "تنظيف الأرائك والسجاد في باريس، من 70 €",
        "description": "تنظيف الأرائك والكراسي والسجاد في إيل دو فرانس من 70 €. حقن واستخراج في العمق، بقع مُعالَجة، أقمشة مُطهَّرة وسريعة الجفاف. عرض سعر خلال 24 ساعة."
      },
      "service": {
        "name": "تنظيف الأرائك والكراسي والسجاد",
        "description": "تنظيف عميق لأقمشة التنجيد بالحقن والاستخراج، في إيل دو فرانس.",
        "serviceType": "تنظيف أقمشة التنجيد",
        "priceFrom": 70
      },
      "blocks": [
        {
          "type": "pageHero",
          "content": {
            "eyebrow": "أرائك · كراسي · سجاد",
            "titre": "أقمشتكم تستعيد نضارتها",
            "intro": "أريكة باهتة، سجادة عليها أثر، رائحة تستقرّ: يذهب الحقن والاستخراج للبحث عن الوسخ في قلب اللِيف، حيث تتوقّف المكنسة.",
            "breadcrumb": [
              {
                "label": "الرئيسية",
                "href": "/"
              },
              {
                "label": "الخدمات",
                "href": "/services"
              },
              {
                "label": "أرائك وسجاد"
              }
            ],
            "ctaPrimaire": {
              "label": "اطلب عرض سعر",
              "href": "/contact"
            },
            "ctaSecondaire": {
              "label": "+33 7 48 32 20 29",
              "href": "tel:+33748322029"
            }
          }
        },
        {
          "type": "contenu",
          "content": {
            "titre": "الحقن والاستخراج، في العمق",
            "paragraphes": [
              "تقوم الطريقة على رشّ محلول منظّف في قلب القماش، ثم شفطه فوراً مع الوسخ المُذاب. النتيجة: تُعالَج البقع، ويُزال العُثّ والروائح، ويخرج القماش مُطهَّراً بدل أن يُفرَك في السطح فقط. يستغرق الجفاف عادة بضع ساعات، حسب السُّمك وتهوية الغرفة.",
              "نتدخّل على الأرائك القماشية والكراسي والمقاعد المبطّنة والفرشات والسجاد. تُحدَّد كل مادة قبل أي حركة: الصوف والقطن والاصطناعي والألياف الرقيقة لا تستدعي الجرعة نفسها ولا الحرارة نفسها. أمّا البقع العنيدة فتُعالَج مسبقاً باليد.",
              "ينطلق تنظيف كرسي أو سجادة من 70 €، وتُسعَّر القطع الكبيرة والأرائك الزاوية حسب حجمها. نأتي إلى بيتكم بكل المعدّات: لا شيء عليكم نقله."
            ]
          }
        },
        {
          "type": "faq",
          "content": {
            "titre": "أسئلة حول تنظيف الأقمشة",
            "items": [
              {
                "question": "كم تحتاج الأريكة لتجفّ؟",
                "reponse": "احسبوا عموماً من ساعتين إلى أربع ساعات، حسب سُمك الحشو وتهوية الغرفة. نضبط الاستخراج لسحب أقصى قدر من الرطوبة وتقصير مدة الجفاف."
              },
              {
                "question": "هل تزول كل البقع؟",
                "reponse": "تتلاشى الأغلبية الساحقة بوضوح، خصوصاً إن كانت البقعة حديثة. بعض الآثار القديمة أو الدائمة قد تبقى ظاهرة: نكون صادقين بشأن النتيجة المتوقّعة قبل التدخّل."
              },
              {
                "question": "هل تعالجون كذلك الفرشات والسجاد الرقيق؟",
                "reponse": "نعم. الفرشات والسجاد الصوفي أو الحريري والألياف الرقيقة تُنظَّف بجرعة وطريقة ملائمتين للمادة، بعد اختبار خفيّ على منطقة قليلة الظهور."
              }
            ]
          },
          "variant": "deux-colonnes"
        },
        {
          "type": "services",
          "content": {
            "titre": "في الزيارة نفسها",
            "items": [
              {
                "nom": "تنظيف منزلي",
                "icone": "Home",
                "description": "الصيانة الكاملة للمنزل، إضافةً إلى الأقمشة.",
                "href": "/menage-domicile"
              },
              {
                "nom": "تنظيف الزجاج",
                "icone": "Sparkles",
                "description": "نوافذ نظيفة ترافق التنظيف الكبير.",
                "href": "/nettoyage-vitres"
              },
              {
                "nom": "المكاتب والمحلات المهنية",
                "icone": "Briefcase",
                "description": "مقاعد الاستقبال وكراسي الاجتماعات مُطهَّرة.",
                "href": "/nettoyage-professionnels"
              }
            ]
          },
          "variant": "grille-icones"
        },
        {
          "type": "cta",
          "content": {
            "titre": "أريكة أو سجادة لإنعاشها؟",
            "sousTitre": "أرسلوا لنا صورة عبر واتساب: سيكون التقدير أكثر دقّة.",
            "ctaPrimaire": {
              "label": "اطلب عرض سعر",
              "href": "/contact"
            },
            "ctaSecondaire": {
              "label": "+33 7 48 32 20 29",
              "href": "tel:+33748322029"
            }
          },
          "variant": "encadre"
        }
      ]
    },
    {
      "slug": "remise-en-etat",
      "label": "الترميم بعد الأشغال",
      "navHidden": true,
      "meta": {
        "title": "الترميم بعد الأشغال في باريس، من 300 €",
        "description": "ترميم بعد الأشغال أو الانتقال في إيل دو فرانس، من 300 €. غبار الورشة وآثار الطلاء والأرضيات تُستعاد غرفةً غرفة. عرض سعر مجاني خلال 24 ساعة."
      },
      "service": {
        "name": "الترميم بعد الأشغال أو الانتقال",
        "description": "تنظيف كامل لمنزل أو محلّ بعد أشغال أو قبل جرد الخروج، في إيل دو فرانس.",
        "serviceType": "تنظيف الترميم بعد الأشغال",
        "priceFrom": 300
      },
      "blocks": [
        {
          "type": "pageHero",
          "content": {
            "eyebrow": "بعد الأشغال · بعد الانتقال",
            "titre": "من الورشة إلى المفاتيح، مكان جاهز للسكن",
            "intro": "تترك نهاية الأشغال دائماً طبقة من الغبار الناعم وآثار طلاء وملصقات في كل مكان. نستعيد المكان بعمق كي يكون جاهزاً للسكن أو للتسليم.",
            "breadcrumb": [
              {
                "label": "الرئيسية",
                "href": "/"
              },
              {
                "label": "الخدمات",
                "href": "/services"
              },
              {
                "label": "الترميم بعد الأشغال"
              }
            ],
            "ctaPrimaire": {
              "label": "اطلب عرض سعر",
              "href": "/contact"
            },
            "ctaSecondaire": {
              "label": "+33 7 48 32 20 29",
              "href": "tel:+33748322029"
            }
          }
        },
        {
          "type": "contenu",
          "content": {
            "titre": "بعد أشغال أو قبل جرد الخروج",
            "paragraphes": [
              "الترميم بعد الأشغال خدمة قائمة بذاتها: لا يمكن ارتجالها بتنظيف بسيط. نزيل غبار الورشة الذي يتسلّل في كل مكان، وبقايا الجبس والغراء، وآثار الطلاء واللاصق على الزجاج والأرضيات، والملصقات على النجارة الجديدة، ثم نغسل جميع الأسطح حتى الأفاريز والمفاتيح الكهربائية.",
              "تصلح هذه الخدمة كذلك للانتقالات: منزل يُترَك ناصعاً قبل جرد الخروج، أو مسكن جديد يُنظَّف قبل وضع الصناديق. وللمهنيين، نستعيد محلّاً بعد تهيئة أو قبل تسليم. تُراجَع كل غرفة معكم في نهاية التدخّل.",
              "ينطلق الترميم من 300 € ويتوقّف على المساحة وحجم الأشغال والحالة الأولية. تكفي معاينة في المكان، أو بضع صور، لإعداد عرض سعر دقيق."
            ]
          }
        },
        {
          "type": "faq",
          "content": {
            "titre": "أسئلة حول الترميم بعد الأشغال",
            "items": [
              {
                "question": "ما الفرق مع تنظيف عادي؟",
                "reponse": "يتصدّى الترميم لأوساخ لا تعالجها الصيانة الاعتيادية: غبار ورشة ناعم متغلغل، رذاذ طلاء، غراء، كلس على الأدوات الصحّية الجديدة. يستلزم مواد خاصة ووقتاً أطول بكثير لكل متر مربّع."
              },
              {
                "question": "هل تتدخّلون قبل جرد الخروج؟",
                "reponse": "نعم، طلبٌ متكرّر. نُعيد المنزل في حالة أنيقة لمواجهة الجرد بهدوء. أخبرونا بالأجل النهائي كي نضبط التدخّل في الوقت المناسب."
              },
              {
                "question": "كيف نحصل على سعر عادل لهذا النوع من الأشغال؟",
                "reponse": "الأفضل معاينة سريعة في المكان، أو بضع صور ممثّلة للغرف. نلائم عرض السعر مع الحالة الحقيقية بدل جزاف أعمى، تفادياً لأي مفاجأة سيّئة."
              }
            ]
          },
          "variant": "deux-colonnes"
        },
        {
          "type": "services",
          "content": {
            "titre": "خدمات مرتبطة",
            "items": [
              {
                "nom": "تنظيف الزجاج",
                "icone": "Sparkles",
                "description": "آثار الطلاء واللاصق تُزال من الأسطح الزجاجية.",
                "href": "/nettoyage-vitres"
              },
              {
                "nom": "تنظيف منزلي",
                "icone": "Home",
                "description": "صيانة منتظمة بعد إعادة المنزل إلى حالته الجديدة.",
                "href": "/menage-domicile"
              },
              {
                "nom": "العمارات والأجزاء المشتركة",
                "icone": "Building2",
                "description": "أجزاء مشتركة تُستعاد بعد أشغال في العمارة.",
                "href": "/nettoyage-copropriete"
              }
            ]
          },
          "variant": "grille-icones"
        },
        {
          "type": "cta",
          "content": {
            "titre": "ورشة انتهت للتوّ؟",
            "sousTitre": "أرسلوا لنا المساحة وبضع صور: يخرج عرض السعر خلال 24 ساعة.",
            "ctaPrimaire": {
              "label": "اطلب عرض سعر",
              "href": "/contact"
            },
            "ctaSecondaire": {
              "label": "+33 7 48 32 20 29",
              "href": "tel:+33748322029"
            }
          },
          "variant": "encadre"
        }
      ]
    },
    {
      "slug": "tarifs",
      "label": "الأسعار",
      "meta": {
        "title": "أسعار التنظيف في باريس وإيل دو فرانس",
        "description": "تنظيف من 35 €/الساعة، زجاج من 100 €، أريكة من 70 €، مكاتب من 120 €، ترميم من 300 €. قدّروا ميزانيتكم عبر الإنترنت، سعر ثابت خلال 24 ساعة."
      },
      "blocks": [
        {
          "type": "pageHero",
          "content": {
            "eyebrow": "الأسعار والتقدير",
            "titre": "أسعار انطلاق مَعروضة بوضوح",
            "intro": "تنظيف منزلي بـ 35 €/الساعة، زجاج من 100 €، أريكة من 70 €، مكاتب من 120 €، شرفة من 120 €، ترميم من 300 €، أجزاء مشتركة للعمارة حسب عرض السعر. كوّنوا تقديركم أدناه، ثم استلموا سعراً ثابتاً خلال 24 ساعة."
          }
        },
        {
          "type": "contenu",
          "content": {
            "eyebrow": "التزامنا بالسعر",
            "titre": "أسعار واضحة، بلا مفاجآت مزعجة",
            "paragraphes": [
              "نعرض أسعار انطلاقنا بكل شفافية. يتوقّف المبلغ النهائي على ثلاثة عناصر بسيطة: المساحة المطلوب معالجتها، ووتيرة المرور، وحالة المكان عند بدء العمل. وما نكتبه في عرض السعر هو بالضبط ما تدفعونه.",
              "عرض السعر مجاني ومفصّل وبلا التزام. يصلكم خلال 24 ساعة، ونبقى في المتناول لتعديله معكم إن تغيّرت حاجتكم في الطريق."
            ]
          }
        },
        {
          "type": "tarifs",
          "mode": "grille",
          "content": {
            "titre": "أسعار انطلاقنا",
            "intro": "نظرة صادقة على حدّنا الأدنى من الأسعار، خدمةً خدمة. وللحصول على مبلغ دقيق، اطلبوا عرض سعركم المجاني.",
            "items": [
              {
                "nom": "تنظيف منزلي",
                "prix": "35 €/الساعة",
                "description": "صيانة منتظمة أو ظرفية لمنزلكم.",
                "inclus": [
                  "عاملة قارّة مخصّصة",
                  "المعدات والمواد مُوفَّرة",
                  "على إيقاعكم، من الاثنين إلى السبت"
                ]
              },
              {
                "nom": "تنظيف الزجاج",
                "prix": "من 100 €",
                "description": "واجهات ونوافذ زجاجية وشبابيك، من الجهتين.",
                "inclus": [
                  "الإطارات والحوافّ مشمولة",
                  "مراجعة في عكس الضوء"
                ]
              },
              {
                "nom": "الأرائك والكراسي والسجاد",
                "prix": "من 70 €",
                "description": "حقن واستخراج في العمق، في المنزل.",
                "inclus": [
                  "معالجة مسبقة للبقع باليد",
                  "جفاف خلال ساعات"
                ]
              },
              {
                "nom": "المكاتب والمحلات المهنية",
                "prix": "من 120 €",
                "description": "مكاتب ومحلات ومطاعم ومطابخ مهنية.",
                "inclus": [
                  "خارج ساعات العمل",
                  "إمكانية عقد دوري"
                ]
              },
              {
                "nom": "تنظيف الشرفة",
                "prix": "من 120 €",
                "description": "أرضيات وبلاط خارجي تُزال دهونه وطحالبه.",
                "inclus": [
                  "ضغط ملائم لنوع المادة"
                ]
              },
              {
                "nom": "الترميم بعد الأشغال",
                "prix": "من 300 €",
                "description": "بعد ورشة أو انتقال.",
                "inclus": [
                  "إزالة غبار الورشة والآثار",
                  "مراجعة غرفةً غرفة"
                ]
              },
              {
                "nom": "العمارات والأجزاء المشتركة",
                "prix": "حسب عرض السعر",
                "description": "عقد صيانة منتظم للأجزاء المشتركة.",
                "inclus": [
                  "جدول ثابت",
                  "مسؤول وحيد للمتصرّف"
                ]
              }
            ],
            "note": "أسعار انطلاق إرشادية. عرض سعر ثابت يُعاد خلال 24 ساعة بعد دراسة طلبكم.",
            "cta": {
              "label": "قدّر عرض سعري المجاني",
              "href": "/contact"
            }
          }
        },
        {
          "type": "cta",
          "content": {
            "titre": "مشروع أكثر تعقيداً؟",
            "sousTitre": "حجم كبير، عدة مواقع، حاجة متكرّرة: صِفوها، ويبقى عرض السعر مجانياً.",
            "ctaPrimaire": {
              "label": "اتصلوا بنا",
              "href": "/contact"
            },
            "ctaSecondaire": {
              "label": "+33 7 48 32 20 29",
              "href": "tel:+33748322029"
            }
          },
          "variant": "encadre"
        }
      ]
    },
    {
      "slug": "zone-intervention",
      "label": "منطقة التدخّل",
      "navHidden": true,
      "meta": {
        "title": "منطقة التدخّل — باريس وإيل دو فرانس",
        "description": "تتدخّل RD NET&PROPRE في باريس وأقاليم إيل دو فرانس الثمانية: الحزام الأول والثاني. عمارات ومكاتب وأفراد، عرض سعر خلال 24 ساعة."
      },
      "blocks": [
        {
          "type": "pageHero",
          "content": {
            "eyebrow": "منطقة التدخّل",
            "titre": "كل إيل دو فرانس، انطلاقاً من باريس",
            "intro": "قاعدتنا باريسية، لكن ميداننا يغطّي أقاليم المنطقة الثمانية. هكذا ننظّم تنقّلاتنا، من العاصمة إلى الحزام الثاني."
          }
        },
        {
          "type": "zone",
          "mode": "carte",
          "content": {
            "titre": "ثلاث حلقات، متطلّب واحد",
            "intro": "سواء كان مكانكم في دائرة باريسية أو في الحزام الأول أو في أطراف المنطقة، نطبّق المنهج نفسه والمراقبة نفسها. بلديتكم غير مدرجة؟ اسألوا: إن كانت في إيل دو فرانس، نأتي.",
            "rayonKm": 60,
            "mapEmbedUrl": "https://www.openstreetmap.org/export/embed.html?bbox=1.44%2C48.12%2C3.56%2C49.24&layer=mapnik&marker=48.8566%2C2.3522",
            "zones": [
              {
                "region": "باريس المدينة (75)",
                "principale": "Paris",
                "villes": [
                  "وسط باريس",
                  "الضفة اليسرى",
                  "الضفة اليمنى",
                  "الدوائر العشرون"
                ]
              },
              {
                "region": "الحزام الأول (92 · 93 · 94)",
                "principale": "Boulogne-Billancourt",
                "villes": [
                  "Boulogne-Billancourt",
                  "Neuilly-sur-Seine",
                  "Levallois-Perret",
                  "Nanterre",
                  "Courbevoie",
                  "Montreuil",
                  "Saint-Denis",
                  "Aubervilliers",
                  "Créteil",
                  "Vitry-sur-Seine",
                  "Ivry-sur-Seine"
                ]
              },
              {
                "region": "الحزام الثاني (77 · 78 · 91 · 95)",
                "principale": "Versailles",
                "villes": [
                  "Versailles",
                  "Saint-Germain-en-Laye",
                  "Argenteuil",
                  "Cergy",
                  "Sarcelles",
                  "Évry-Courcouronnes",
                  "Meaux",
                  "Melun"
                ]
              }
            ]
          }
        },
        {
          "type": "cta",
          "content": {
            "titre": "مكانكم في مكان ما على هذه الخريطة؟",
            "sousTitre": "أعطونا البلدية ونوع الفضاء: نؤكّد التنقّل ونضع له سعراً.",
            "ctaPrimaire": {
              "label": "اطلب عرض سعر",
              "href": "/contact"
            },
            "ctaSecondaire": {
              "label": "+33 7 48 32 20 29",
              "href": "tel:+33748322029"
            }
          },
          "variant": "encadre"
        }
      ]
    },
    {
      "slug": "a-propos",
      "label": "من نحن",
      "navHidden": true,
      "meta": {
        "title": "مقاربتنا للتنظيف في إيل دو فرانس",
        "description": "RD NET&PROPRE، شركة تنظيف مقرّها باريس: عمّال قارّون، مراقبة منهجية واستقبال متعدّد اللغات في خدمة منطقة باريس."
      },
      "blocks": [
        {
          "type": "pageHero",
          "content": {
            "eyebrow": "من نحن",
            "titre": "RD NET&PROPRE، النظافة على محمل الجدّ",
            "intro": "شركة من منطقة باريس تضع الانتظام والكتمان ومراقبة النتيجة في صميم كل تدخّل — لمتصرّفي العمارات والشركات والأفراد."
          }
        },
        {
          "type": "contenu",
          "content": {
            "titre": "طريقتنا في العمل",
            "paragraphes": [
              "RD NET&PROPRE شركة تنظيف مقرّها باريس، في خدمة كامل إيل دو فرانس. بنينا مقاربتنا حول قناعة واحدة: النظافة لا تُقاس لحظة المغادرة، بل عبر الزمن. مدخل يبقى نظيفاً بين مرورين، مكتب يستقبل الفرق دون مأخذ، بيت يشعر فيه المرء بالراحة: تلك هي النتيجة الحقيقية.",
              "لبلوغ ذلك، نعتمد على عمّال قارّين ومدرَّبين وكتومين بدل مناوبة مجهولة. لكل زبون مُحاور يعرف أماكنه وتطلّعاته. ولأننا نعمل غالباً في بيوت الناس أو في فضاءات حسّاسة، تأتي الثقة واحترام المكان قبل كل شيء.",
              "نستقبل زبائننا بالفرنسية والإنجليزية والإسبانية والعربية: في باريس كما في الحزام، يجب أن يستطيع كلٌّ شرح حاجته دون حاجز وأن يتلقّى جواباً واضحاً."
            ]
          }
        },
        {
          "type": "etapes",
          "content": {
            "eyebrow": "معاييرنا",
            "titre": "أربعة التزامات نتمسّك بها",
            "items": [
              {
                "icone": "ShieldCheck",
                "titre": "الثقة",
                "texte": "عمّال جادّون وكتومون، يحترمون أماكنكم وأغراضكم وخصوصيتكم."
              },
              {
                "icone": "Repeat",
                "titre": "الانتظام",
                "texte": "الفريق نفسه من مرة إلى أخرى، جدول مُحترَم ونتيجة ثابتة عبر الزمن."
              },
              {
                "icone": "SearchCheck",
                "titre": "المراقبة",
                "texte": "تُراجَع كل منطقة قبل المغادرة: لا شيء يُترَك للصدفة."
              },
              {
                "icone": "Languages",
                "titre": "القُرب",
                "texte": "استقبال بأربع لغات ومُحاور يجيبكم فعلاً، بلغتكم."
              }
            ]
          },
          "variant": "timeline-verticale"
        },
        {
          "type": "cta",
          "content": {
            "titre": "تريدون أن تعهدوا إلينا بمكان؟",
            "sousTitre": "لنتحدّث عن حاجتكم: الحديث لا يُلزم بشيء وعرض السعر مجاني.",
            "ctaPrimaire": {
              "label": "اطلب عرض سعر",
              "href": "/contact"
            },
            "ctaSecondaire": {
              "label": "اتصلوا بنا",
              "href": "/contact"
            }
          },
          "variant": "encadre"
        }
      ]
    },
    {
      "slug": "contact",
      "label": "اتصال",
      "meta": {
        "title": "اتصال — تنظيف في باريس وإيل دو فرانس",
        "description": "هاتف أو واتساب أو نموذج: صِفوا حاجتكم للتنظيف في إيل دو فرانس. ردّ وعرض سعر مجاني خلال 24 ساعة، بالفرنسية أو الإنجليزية أو الإسبانية أو العربية."
      },
      "blocks": [
        {
          "type": "pageHero",
          "content": {
            "eyebrow": "اتصال",
            "titre": "لنتحدّث عن المكان المطلوب تنظيفه",
            "intro": "اتصال أو واتساب أو النموذج: اختاروا القناة التي تناسبكم. صِفوا نوع الفضاء والمساحة والوتيرة — يخرج عرض سعركم خلال 24 ساعة."
          }
        },
        {
          "type": "contact",
          "content": {
            "titre": "طلب عرض سعر",
            "intro": "بيّنوا الخدمة المطلوبة وبلديتكم والوقت المتوخّى: نُعدّ تقديركم ونعيده إليكم خلال 24 ساعة. خطّان للتواصل معنا: 07 48 32 20 29 و07 58 08 61 83.",
            "form": true,
            "formMode": "demande-intervention",
            "telephone": "07 48 32 20 29",
            "whatsapp": "+33 7 48 32 20 29",
            "email": "rd.nettoyagepropre@gmail.com",
            "horaires": [
              {
                "jour": "الإثنين – السبت",
                "heures": "08:00 – 22:00"
              },
              {
                "jour": "الأحد",
                "heures": "مغلق"
              }
            ],
            "services": [
              "عمارة / أجزاء مشتركة",
              "مكاتب ومحلات مهنية",
              "مطعم / مطبخ مهني",
              "تنظيف الزجاج",
              "تنظيف منزلي",
              "أريكة وكرسي وسجادة",
              "تنظيف الشرفة",
              "الترميم بعد الأشغال (أشغال / انتقال)",
              "أخرى / لا أعرف بعد"
            ],
            "villes": [
              "Paris",
              "Boulogne-Billancourt",
              "Neuilly-sur-Seine",
              "Levallois-Perret",
              "Nanterre",
              "Courbevoie",
              "Montreuil",
              "Saint-Denis",
              "Aubervilliers",
              "Créteil",
              "Vitry-sur-Seine",
              "Ivry-sur-Seine",
              "Versailles",
              "Argenteuil",
              "Cergy",
              "بلدية أخرى في إيل دو فرانس"
            ],
            "mapEmbedUrl": "https://www.openstreetmap.org/export/embed.html?bbox=1.44%2C48.12%2C3.56%2C49.24&layer=mapnik&marker=48.8566%2C2.3522",
            "confidentialiteHref": "/confidentialite"
          }
        }
      ]
    }
  ]
}
